django_goolytics-0.1.0.data/scripts/goolytic-setup.bat
goolytics/__init__.py
goolytics/admin.py
goolytics/apps.py
goolytics/models.py
goolytics/security.py
goolytics/tests.py
goolytics/urls.py
goolytics/views.py
goolytics/migrations/0001_initial.py
goolytics/migrations/0002_auto_20200625_0653.py
goolytics/migrations/__init__.py
django_goolytics-0.1.0.dist-info/LICENSE
django_goolytics-0.1.0.dist-info/METADATA
django_goolytics-0.1.0.dist-info/WHEEL
django_goolytics-0.1.0.dist-info/top_level.txt
django_goolytics-0.1.0.dist-info/RECORD
